testit/__init__.py
testit/main.py
testit/run.py
testit/run_util.py
testit/testit.py
testit/testit_util.py
testit/templates/config.test
testit/templates/testit_golden.py
testitpy-0.4.dist-info/licenses/LICENSE
testitpy-0.4.dist-info/METADATA
testitpy-0.4.dist-info/WHEEL
testitpy-0.4.dist-info/entry_points.txt
testitpy-0.4.dist-info/top_level.txt
testitpy-0.4.dist-info/RECORD
