Metadata-Version: 2.4
Name: testitpy
Version: 0.4
Summary: A tool for verifying RTL and FPGA models using custom SW applications
Author-email: Tommaso Terzano <tommaso.terzano@gmail.com>
License:                     GNU GENERAL PUBLIC LICENSE
Requires-Python: >=3.7
License-File: LICENSE
Requires-Dist: rich
Requires-Dist: pexpect
Requires-Dist: numpy
Requires-Dist: pyserial
Requires-Dist: hjson
Requires-Dist: importlib_resources
Dynamic: license-file
